cetino/__init__.py
cetino/db/__init__.py
cetino/db/dialect.py
cetino/db/sql_builder.py
cetino/db/_base/__init__.py
cetino/db/_base/base.py
cetino/db/mysql/__init__.py
cetino/db/mysql/sql_builder.py
cetino/db/mysql/type.py
cetino/db/postgre/__init__.py
cetino/db/postgre/sql_builder.py
cetino/db/postgre/type.py
cetino/db/sqlite/__init__.py
cetino/db/sqlite/_decorator.py
cetino/db/sqlite/sql_builder.py
cetino/db/sqlite/storage.py
cetino/db/sqlite/table_storage.py
cetino/db/sqlite/type.py
cetino/fs/__init__.py
cetino/fs/csv/__init__.py
cetino/fs/csv/storage.py
cetino/utils/__init__.py
cetino/utils/io_utils.py
cetino/utils/log_utils.py
cetino/utils/storage_utils.py
cetino/utils/string_utils.py
test/__init__.py
test/db/__init__.py
test/db/sqlite/__init__.py
test/db/sqlite/sql_builder.py
test/db/sqlite/table_storage.py
cetino-0.1.3.dist-info/LICENCE
cetino-0.1.3.dist-info/METADATA
cetino-0.1.3.dist-info/WHEEL
cetino-0.1.3.dist-info/top_level.txt
cetino-0.1.3.dist-info/RECORD
